{
  "transactions": [
    {
      "id": 1,
      "description": "Desenvolvimento de site",
      "type": "income",
      "category": "Venda",
      "price": 14000,
      "createdAt": "2022-08-15T08:21:31.132Z"
    },
    {
      "id": 2,
      "description": "Banco de dados",
      "type": "outcome",
      "category": "Gastos pontuais",
      "price": 5000,
      "createdAt": "2022-07-17T08:21:31.132Z"
    },
    {
      "description": "Desenvolvimento de App",
      "price": 10000,
      "category": "Venda",
      "type": "income",
      "createdAt": "2022-08-16T09:39:05.442Z",
      "id": 3
    },
    {
      "description": "Supermercado",
      "price": 500,
      "category": "Compras",
      "type": "outcome",
      "createdAt": "2022-08-16T09:56:38.951Z",
      "id": 4
    },
    {
      "description": "Cadeira Gamer",
      "price": 2000,
      "category": "Escritório",
      "type": "outcome",
      "createdAt": "2022-08-17T08:58:38.618Z",
      "id": 5
    }
  ]
}